[
	{
		"Time": "2018-03-14 10:28:37.111",
		"GYRO_X": 0.00000,
		"GYRO_Y": 0.00000,
		"GYRO_Z": 0.00000,
		"GYRO_Z": 0.00000,
		"ACCEL_X": 0.00000,
		"ACCEL_Y": 0.00000,
		"ACCEL_Z": 0.00000
	},
	{
		"Time": "2018-03-14 10:28:37.131",
		"GYRO_X": 1.00000,
		"GYRO_Y": 1.00000,
		"GYRO_Z": 1.00000,
		"ACCEL_X": 1.00000,
		"ACCEL_Y": 1.00000,
		"ACCEL_Z": 1.00000
	},
	{
		"Time": "2018-03-14 10:28:37.151",
		"GYRO_X": 2.00000,
		"GYRO_Y": 2.00000,
		"GYRO_Z": 2.00000,
		"ACCEL_X": 2.00000,
		"ACCEL_Y": 2.00000,
		"ACCEL_Z": 2.00000
	},
	{
		"Time": "2018-03-14 10:28:37.171",
		"GYRO_X": 3.00000,
		"GYRO_Y": 3.00000,
		"GYRO_Z": 3.00000,
		"ACCEL_X": 3.00000,
		"ACCEL_Y": 3.00000,
		"ACCEL_Z": 3.00000
	}
]